hello_world/__init__.py
hello_world/cli.py
hello_world_deshiitha-0.1.dist-info/METADATA
hello_world_deshiitha-0.1.dist-info/WHEEL
hello_world_deshiitha-0.1.dist-info/entry_points.txt
hello_world_deshiitha-0.1.dist-info/top_level.txt
hello_world_deshiitha-0.1.dist-info/RECORD
