Metadata-Version: 2.1
Name: hello_world_deshiitha
Version: 0.1
Summary: A simple hello world package  and uploading to pypi and adding it o the gitlab trial3
Author: deshi
Author-email: deshithabollina28@gmail.com
Requires-Dist: click
